upcounting/__init__.py
upcounting/core/__init__.py
upcounting/tests/__init__.py
upcounting/tests/test_0.py
upcounting-1.0.5.dist-info/licenses/LICENSE.txt
upcounting-1.0.5.dist-info/METADATA
upcounting-1.0.5.dist-info/WHEEL
upcounting-1.0.5.dist-info/top_level.txt
upcounting-1.0.5.dist-info/RECORD
