Metadata-Version: 2.4
Name: upcounting
Version: 1.0.5
Summary: This project counts until meeting a condition. Infinite counting is also supported.
Author-email: Johannes <johannes.programming@gmail.com>
License: The MIT License (MIT)
Project-URL: Download, https://pypi.org/project/upcounting/#files
Project-URL: Index, https://pypi.org/project/upcounting/
Project-URL: Source, https://github.com/johannes-programming/upcounting/
Project-URL: Website, http://upcounting.johannes-programming.online/
Classifier: Development Status :: 5 - Production/Stable
Classifier: License :: OSI Approved :: MIT License
Classifier: Natural Language :: English
Classifier: Operating System :: OS Independent
Classifier: Programming Language :: Python
Classifier: Programming Language :: Python :: 3
Classifier: Programming Language :: Python :: 3 :: Only
Classifier: Typing :: Typed
Requires-Python: >=3.11
License-File: LICENSE.txt
Dynamic: license-file
